easy_start_chanjet/__init__.py
easy_start_chanjet/zkhb/__init__.py
easy_start_chanjet/zkhb/http.py
easy_start_chanjet/zkhb/webservice.py
easy_start_chanjet-0.2.0.dist-info/licenses/LICENSE
easy_start_chanjet-0.2.0.dist-info/METADATA
easy_start_chanjet-0.2.0.dist-info/WHEEL
easy_start_chanjet-0.2.0.dist-info/top_level.txt
easy_start_chanjet-0.2.0.dist-info/RECORD
