Metadata-Version: 2.4
Name: easy-start-chanjet
Version: 0.2.0
Summary: easy-start-chanjet 是一个为畅捷通中科华博系统提供集成接口的Python开发包，旨在简化与畅捷通中科华博API的交互过程，提供便捷的HTTP和WebService调用方式。
Home-page: https://gitee.com/guolei19850528/easy_start_chanjet
Author: guolei
Author-email: 174000902@qq.com
Classifier: Programming Language :: Python :: 3
Classifier: License :: OSI Approved :: MIT License
Classifier: Operating System :: OS Independent
Requires-Python: >=3.6
License-File: LICENSE
Requires-Dist: httpx
Requires-Dist: beautifulsoup4
Requires-Dist: lxml
Requires-Dist: html5lib
Requires-Dist: xmltodict
Requires-Dist: arrow
Requires-Dist: jsonschema
Dynamic: author
Dynamic: author-email
Dynamic: classifier
Dynamic: description
Dynamic: description-content-type
Dynamic: home-page
Dynamic: license-file
Dynamic: requires-dist
Dynamic: requires-python
Dynamic: summary
